{"head": {"vars": ["property", "hasValue", "isValueOf"]}, "results": {"bindings": [{"property": {"type": "uri", "value": "http://purl.org/dc/elements/1.1/date"}, "hasValue": {"datatype": "http://www.w3.org/2001/XMLSchema#int", "type": "typed-literal", "value": "0"}}, {"property": {"type": "uri", "value": "http://purl.org/dc/elements/1.1/title"}, "hasValue": {"type": "literal", "value": "Uninvited (extended mix)"}}, {"property": {"type": "uri", "value": "http://purl.org/ontology/mo/length"}, "hasValue": {"datatype": "http://www.w3.org/2001/XMLSchema#int", "type": "typed-literal", "value": "330000"}}, {"property": {"type": "uri", "value": "http://purl.org/ontology/mo/musicbrainz"}, "hasValue": {"type": "uri", "value": "http://musicbrainz.org/track/6abb2a2d-1327-4359-8a1f-387d3d1598d9"}}, {"property": {"type": "uri", "value": "http://purl.org/ontology/mo/track_number"}, "hasValue": {"datatype": "http://www.w3.org/2001/XMLSchema#int", "type": "typed-literal", "value": "2"}}, {"property": {"type": "uri", "value": "http://www.w3.org/1999/02/22-rdf-syntax-ns#type"}, "hasValue": {"type": "uri", "value": "http://purl.org/ontology/mo/Track"}}, {"property": {"type": "uri", "value": "http://www.w3.org/2000/01/rdf-schema#label"}, "hasValue": {"type": "literal", "value": "Uninvited (extended mix)"}}, {"property": {"type": "uri", "value": "http://xmlns.com/foaf/0.1/maker"}, "hasValue": {"type": "uri", "value": "http://dbtune.org/musicbrainz/resource/artist/0057cec9-4c2d-4f92-98a9-4d6457cbcd4b"}}, {"property": {"type": "uri", "value": "http://purl.org/ontology/mo/published_as"}, "isValueOf": {"type": "uri", "value": "http://dbtune.org/musicbrainz/resource/signal/6abb2a2d-1327-4359-8a1f-387d3d1598d9"}}, {"property": {"type": "uri", "value": "http://purl.org/ontology/mo/track"}, "isValueOf": {"type": "uri", "value": "http://dbtune.org/musicbrainz/resource/record/1eccd966-ed7b-40e1-b956-2e8b949a6416"}}]}}