{"head": {"vars": ["property", "hasValue", "isValueOf"]}, "results": {"bindings": [{"property": {"type": "uri", "value": "http://purl.org/dc/elements/1.1/date"}, "hasValue": {"datatype": "http://www.w3.org/2001/XMLSchema#int", "type": "typed-literal", "value": "0"}}, {"property": {"type": "uri", "value": "http://purl.org/dc/elements/1.1/title"}, "hasValue": {"type": "literal", "value": "Dreams of an Absolution"}}, {"property": {"type": "uri", "value": "http://purl.org/ontology/mo/length"}, "hasValue": {"datatype": "http://www.w3.org/2001/XMLSchema#int", "type": "typed-literal", "value": "318000"}}, {"property": {"type": "uri", "value": "http://purl.org/ontology/mo/musicbrainz"}, "hasValue": {"type": "uri", "value": "http://musicbrainz.org/track/c636c3a8-64a6-46dd-a6a9-27aa30dfadbc"}}, {"property": {"type": "uri", "value": "http://purl.org/ontology/mo/track_number"}, "hasValue": {"datatype": "http://www.w3.org/2001/XMLSchema#int", "type": "typed-literal", "value": "2"}}, {"property": {"type": "uri", "value": "http://www.w3.org/1999/02/22-rdf-syntax-ns#type"}, "hasValue": {"type": "uri", "value": "http://purl.org/ontology/mo/Track"}}, {"property": {"type": "uri", "value": "http://www.w3.org/2000/01/rdf-schema#label"}, "hasValue": {"type": "literal", "value": "Dreams of an Absolution"}}, {"property": {"type": "uri", "value": "http://xmlns.com/foaf/0.1/maker"}, "hasValue": {"type": "uri", "value": "http://dbtune.org/musicbrainz/resource/artist/014e1bd5-7d6c-4e07-93bd-3fe263f03654"}}, {"property": {"type": "uri", "value": "http://purl.org/ontology/mo/published_as"}, "isValueOf": {"type": "uri", "value": "http://dbtune.org/musicbrainz/resource/signal/c636c3a8-64a6-46dd-a6a9-27aa30dfadbc"}}, {"property": {"type": "uri", "value": "http://purl.org/ontology/mo/track"}, "isValueOf": {"type": "uri", "value": "http://dbtune.org/musicbrainz/resource/record/d6927122-5a4f-410e-b107-5bd61f3d0e1f"}}]}}