[{"property": {"type": "uri", "value": "http://purl.org/dc/elements/1.1/date"}, "hasValue": {"datatype": "http://www.w3.org/2001/XMLSchema#int", "type": "typed-literal", "value": "0"}}, {"property": {"type": "uri", "value": "http://purl.org/dc/elements/1.1/title"}, "hasValue": {"type": "literal", "value": "Real, Real Gone Live Track"}}, {"property": {"type": "uri", "value": "http://purl.org/ontology/mo/length"}, "hasValue": {"datatype": "http://www.w3.org/2001/XMLSchema#int", "type": "typed-literal", "value": "153000"}}, {"property": {"type": "uri", "value": "http://purl.org/ontology/mo/musicbrainz"}, "hasValue": {"type": "uri", "value": "http://musicbrainz.org/track/f1f43f5e-5a42-47c9-ac4c-232ec3316045"}}, {"property": {"type": "uri", "value": "http://purl.org/ontology/mo/track_number"}, "hasValue": {"datatype": "http://www.w3.org/2001/XMLSchema#int", "type": "typed-literal", "value": "16"}}, {"property": {"type": "uri", "value": "http://www.w3.org/1999/02/22-rdf-syntax-ns#type"}, "hasValue": {"type": "uri", "value": "http://purl.org/ontology/mo/Track"}}, {"property": {"type": "uri", "value": "http://www.w3.org/2000/01/rdf-schema#label"}, "hasValue": {"type": "literal", "value": "Real, Real Gone Live Track"}}, {"property": {"type": "uri", "value": "http://xmlns.com/foaf/0.1/maker"}, "hasValue": {"type": "uri", "value": "http://dbtune.org/musicbrainz/resource/artist/2723f425-8ec1-470b-84a4-7dfcb5df208c"}}, {"property": {"type": "uri", "value": "http://purl.org/ontology/mo/published_as"}, "isValueOf": {"type": "uri", "value": "http://dbtune.org/musicbrainz/resource/signal/f1f43f5e-5a42-47c9-ac4c-232ec3316045"}}, {"property": {"type": "uri", "value": "http://purl.org/ontology/mo/track"}, "isValueOf": {"type": "uri", "value": "http://dbtune.org/musicbrainz/resource/record/24aa0ab9-7fe3-419c-b507-c677eb15a937"}}]