[{"property": {"type": "uri", "value": "http://dbtune.org/musicbrainz/resource/vocab/artist_quality"}, "hasValue": {"datatype": "http://www.w3.org/2001/XMLSchema#short", "type": "typed-literal", "value": "-1"}}, {"property": {"type": "uri", "value": "http://dbtune.org/musicbrainz/resource/vocab/artist_type"}, "hasValue": {"datatype": "http://www.w3.org/2001/XMLSchema#short", "type": "typed-literal", "value": "2"}}, {"property": {"type": "uri", "value": "http://dbtune.org/musicbrainz/resource/vocab/sortname"}, "hasValue": {"type": "literal", "value": "Cut the Shit"}}, {"property": {"type": "uri", "value": "http://purl.org/ontology/mo/musicbrainz"}, "hasValue": {"type": "uri", "value": "http://musicbrainz.org/artist/2d67822d-60f4-40e9-9dee-fa1403b79a53"}}, {"property": {"type": "uri", "value": "http://www.w3.org/1999/02/22-rdf-syntax-ns#type"}, "hasValue": {"type": "uri", "value": "http://purl.org/ontology/mo/MusicArtist"}}, {"property": {"type": "uri", "value": "http://www.w3.org/2000/01/rdf-schema#label"}, "hasValue": {"type": "literal", "value": "Cut the Shit"}}, {"property": {"type": "uri", "value": "http://www.w3.org/2002/07/owl#sameAs"}, "hasValue": {"type": "uri", "value": "http://www.bbc.co.uk/music/artists/2d67822d-60f4-40e9-9dee-fa1403b79a53#artist"}}, {"property": {"type": "uri", "value": "http://xmlns.com/foaf/0.1/name"}, "hasValue": {"type": "literal", "value": "Cut the Shit"}}, {"property": {"type": "uri", "value": "http://xmlns.com/foaf/0.1/maker"}, "isValueOf": {"type": "uri", "value": "http://dbtune.org/musicbrainz/resource/record/2cadb22b-9b5c-486b-be7c-49b92ccf6523"}}, {"property": {"type": "uri", "value": "http://xmlns.com/foaf/0.1/maker"}, "isValueOf": {"type": "uri", "value": "http://dbtune.org/musicbrainz/resource/record/49ab66c4-8135-45f1-90df-aebc861c64a2"}}, {"property": {"type": "uri", "value": "http://xmlns.com/foaf/0.1/maker"}, "isValueOf": {"type": "uri", "value": "http://dbtune.org/musicbrainz/resource/record/a6559ce7-f50d-4203-b693-957ecb4208d8"}}, {"property": {"type": "uri", "value": "http://xmlns.com/foaf/0.1/maker"}, "isValueOf": {"type": "uri", "value": "http://dbtune.org/musicbrainz/resource/record/f96a7027-d162-4729-bcfc-66c469164c11"}}, {"property": {"type": "uri", "value": "http://xmlns.com/foaf/0.1/maker"}, "isValueOf": {"type": "uri", "value": "http://dbtune.org/musicbrainz/resource/track/015a621c-696b-4552-a0c5-08bd8e62e76b"}}, {"property": {"type": "uri", "value": "http://xmlns.com/foaf/0.1/maker"}, "isValueOf": {"type": "uri", "value": "http://dbtune.org/musicbrainz/resource/track/0b3beb02-46cf-468e-8657-ce09ada206df"}}, {"property": {"type": "uri", "value": "http://xmlns.com/foaf/0.1/maker"}, "isValueOf": {"type": "uri", "value": "http://dbtune.org/musicbrainz/resource/track/15339ad8-9ba7-435f-a5e1-69c787159ea8"}}, {"property": {"type": "uri", "value": "http://xmlns.com/foaf/0.1/maker"}, "isValueOf": {"type": "uri", "value": "http://dbtune.org/musicbrainz/resource/track/1917ee64-a99d-4abe-a067-abdb70c186fd"}}, {"property": {"type": "uri", "value": "http://xmlns.com/foaf/0.1/maker"}, "isValueOf": {"type": "uri", "value": "http://dbtune.org/musicbrainz/resource/track/197c3d2b-82cd-4889-a8ce-9c9db8b8030e"}}, {"property": {"type": "uri", "value": "http://xmlns.com/foaf/0.1/maker"}, "isValueOf": {"type": "uri", "value": "http://dbtune.org/musicbrainz/resource/track/2194787c-ef3a-4c4b-a805-080ec2d5c98a"}}, {"property": {"type": "uri", "value": "http://xmlns.com/foaf/0.1/maker"}, "isValueOf": {"type": "uri", "value": "http://dbtune.org/musicbrainz/resource/track/222fc21d-4126-47a9-973a-3e9e31460819"}}, {"property": {"type": "uri", "value": "http://xmlns.com/foaf/0.1/maker"}, "isValueOf": {"type": "uri", "value": "http://dbtune.org/musicbrainz/resource/track/26d8b7a0-3bdd-4b1c-9c63-819c44c0e617"}}, {"property": {"type": "uri", "value": "http://xmlns.com/foaf/0.1/maker"}, "isValueOf": {"type": "uri", "value": "http://dbtune.org/musicbrainz/resource/track/335741a9-3821-48db-a7cb-ba0fc4c387d9"}}, {"property": {"type": "uri", "value": "http://xmlns.com/foaf/0.1/maker"}, "isValueOf": {"type": "uri", "value": "http://dbtune.org/musicbrainz/resource/track/3fda913f-4fd9-4c7d-96f2-2cd00db822de"}}, {"property": {"type": "uri", "value": "http://xmlns.com/foaf/0.1/maker"}, "isValueOf": {"type": "uri", "value": "http://dbtune.org/musicbrainz/resource/track/495db76c-1e70-48dd-aac5-cad0f1b1a378"}}, {"property": {"type": "uri", "value": "http://xmlns.com/foaf/0.1/maker"}, "isValueOf": {"type": "uri", "value": "http://dbtune.org/musicbrainz/resource/track/49fde450-63d4-43bf-9143-adbc74df5635"}}, {"property": {"type": "uri", "value": "http://xmlns.com/foaf/0.1/maker"}, "isValueOf": {"type": "uri", "value": "http://dbtune.org/musicbrainz/resource/track/4e10b188-a294-4efa-89b7-ff5ff4dba805"}}, {"property": {"type": "uri", "value": "http://xmlns.com/foaf/0.1/maker"}, "isValueOf": {"type": "uri", "value": "http://dbtune.org/musicbrainz/resource/track/5075e130-c909-4e64-adf5-2bf445f09f8b"}}, {"property": {"type": "uri", "value": "http://xmlns.com/foaf/0.1/maker"}, "isValueOf": {"type": "uri", "value": "http://dbtune.org/musicbrainz/resource/track/57828e99-560a-434e-b13e-431e3eff188d"}}, {"property": {"type": "uri", "value": "http://xmlns.com/foaf/0.1/maker"}, "isValueOf": {"type": "uri", "value": "http://dbtune.org/musicbrainz/resource/track/5b992964-375f-42da-8096-98ab36639884"}}, {"property": {"type": "uri", "value": "http://xmlns.com/foaf/0.1/maker"}, "isValueOf": {"type": "uri", "value": "http://dbtune.org/musicbrainz/resource/track/618483a3-a463-4532-b2df-b91fa948c1d8"}}, {"property": {"type": "uri", "value": "http://xmlns.com/foaf/0.1/maker"}, "isValueOf": {"type": "uri", "value": "http://dbtune.org/musicbrainz/resource/track/6677f15e-dd81-4fa2-b3a7-d4bbecd99ac8"}}, {"property": {"type": "uri", "value": "http://xmlns.com/foaf/0.1/maker"}, "isValueOf": {"type": "uri", "value": "http://dbtune.org/musicbrainz/resource/track/6d207bc4-f0c6-48c2-a140-c97f6bbf7e3c"}}, {"property": {"type": "uri", "value": "http://xmlns.com/foaf/0.1/maker"}, "isValueOf": {"type": "uri", "value": "http://dbtune.org/musicbrainz/resource/track/6d86fd91-5a30-4dbe-a6f1-b4e30899e30d"}}, {"property": {"type": "uri", "value": "http://xmlns.com/foaf/0.1/maker"}, "isValueOf": {"type": "uri", "value": "http://dbtune.org/musicbrainz/resource/track/72015283-973b-433c-b999-43e5d94f387e"}}, {"property": {"type": "uri", "value": "http://xmlns.com/foaf/0.1/maker"}, "isValueOf": {"type": "uri", "value": "http://dbtune.org/musicbrainz/resource/track/7a96f84f-c5e6-415a-96db-ce512bc48588"}}, {"property": {"type": "uri", "value": "http://xmlns.com/foaf/0.1/maker"}, "isValueOf": {"type": "uri", "value": "http://dbtune.org/musicbrainz/resource/track/7f66ac63-36d1-42f4-b811-d76706b15587"}}, {"property": {"type": "uri", "value": "http://xmlns.com/foaf/0.1/maker"}, "isValueOf": {"type": "uri", "value": "http://dbtune.org/musicbrainz/resource/track/809e9953-42a5-48e0-82d6-bb0ffe6c59ff"}}, {"property": {"type": "uri", "value": "http://xmlns.com/foaf/0.1/maker"}, "isValueOf": {"type": "uri", "value": "http://dbtune.org/musicbrainz/resource/track/81fc79b7-5cbf-4157-9021-8c44008463e9"}}, {"property": {"type": "uri", "value": "http://xmlns.com/foaf/0.1/maker"}, "isValueOf": {"type": "uri", "value": "http://dbtune.org/musicbrainz/resource/track/8580d5e1-c036-412c-92b8-f454b9ff9e4e"}}, {"property": {"type": "uri", "value": "http://xmlns.com/foaf/0.1/maker"}, "isValueOf": {"type": "uri", "value": "http://dbtune.org/musicbrainz/resource/track/879c691b-6b8b-4b65-9c17-0c996465c439"}}, {"property": {"type": "uri", "value": "http://xmlns.com/foaf/0.1/maker"}, "isValueOf": {"type": "uri", "value": "http://dbtune.org/musicbrainz/resource/track/8f5a3cd4-2ff3-4431-bc9b-5315d552b486"}}, {"property": {"type": "uri", "value": "http://xmlns.com/foaf/0.1/maker"}, "isValueOf": {"type": "uri", "value": "http://dbtune.org/musicbrainz/resource/track/95b4bbd7-bd3b-4486-beb6-f765113b82f2"}}, {"property": {"type": "uri", "value": "http://xmlns.com/foaf/0.1/maker"}, "isValueOf": {"type": "uri", "value": "http://dbtune.org/musicbrainz/resource/track/9fc165a3-cdc4-422e-8558-3d3d84b63060"}}, {"property": {"type": "uri", "value": "http://xmlns.com/foaf/0.1/maker"}, "isValueOf": {"type": "uri", "value": "http://dbtune.org/musicbrainz/resource/track/a114a865-40f4-4aba-b58c-f6172cc7e1a8"}}, {"property": {"type": "uri", "value": "http://xmlns.com/foaf/0.1/maker"}, "isValueOf": {"type": "uri", "value": "http://dbtune.org/musicbrainz/resource/track/a20cc7df-acac-41f4-abf7-9513bfd568f2"}}, {"property": {"type": "uri", "value": "http://xmlns.com/foaf/0.1/maker"}, "isValueOf": {"type": "uri", "value": "http://dbtune.org/musicbrainz/resource/track/a32f22c7-dea7-4fb4-b9c8-a8c5145cc342"}}, {"property": {"type": "uri", "value": "http://xmlns.com/foaf/0.1/maker"}, "isValueOf": {"type": "uri", "value": "http://dbtune.org/musicbrainz/resource/track/a83f9009-7719-49b2-a3e9-8d5611975675"}}, {"property": {"type": "uri", "value": "http://xmlns.com/foaf/0.1/maker"}, "isValueOf": {"type": "uri", "value": "http://dbtune.org/musicbrainz/resource/track/aa236d94-afa5-44ba-894b-a5bfd15186a4"}}, {"property": {"type": "uri", "value": "http://xmlns.com/foaf/0.1/maker"}, "isValueOf": {"type": "uri", "value": "http://dbtune.org/musicbrainz/resource/track/ad1210d0-c494-4716-bcbf-9f64986edc37"}}, {"property": {"type": "uri", "value": "http://xmlns.com/foaf/0.1/maker"}, "isValueOf": {"type": "uri", "value": "http://dbtune.org/musicbrainz/resource/track/b1e8116b-d101-44f8-bbeb-ca7e74bd97d8"}}, {"property": {"type": "uri", "value": "http://xmlns.com/foaf/0.1/maker"}, "isValueOf": {"type": "uri", "value": "http://dbtune.org/musicbrainz/resource/track/b3270f42-0242-434d-9efa-9730c0b1aef4"}}, {"property": {"type": "uri", "value": "http://xmlns.com/foaf/0.1/maker"}, "isValueOf": {"type": "uri", "value": "http://dbtune.org/musicbrainz/resource/track/b989452f-a65e-4bb4-8a0c-2f72f78a2748"}}, {"property": {"type": "uri", "value": "http://xmlns.com/foaf/0.1/maker"}, "isValueOf": {"type": "uri", "value": "http://dbtune.org/musicbrainz/resource/track/c597238f-5831-4fbd-88a0-3bb99690dbb1"}}, {"property": {"type": "uri", "value": "http://xmlns.com/foaf/0.1/maker"}, "isValueOf": {"type": "uri", "value": "http://dbtune.org/musicbrainz/resource/track/d05bfb45-b620-4894-874c-093037c9076c"}}, {"property": {"type": "uri", "value": "http://xmlns.com/foaf/0.1/maker"}, "isValueOf": {"type": "uri", "value": "http://dbtune.org/musicbrainz/resource/track/d124b5f7-d5a8-4c4a-ab20-41fa9d17c33f"}}, {"property": {"type": "uri", "value": "http://xmlns.com/foaf/0.1/maker"}, "isValueOf": {"type": "uri", "value": "http://dbtune.org/musicbrainz/resource/track/d2f52f4c-c35e-408b-b3de-44bb86037225"}}, {"property": {"type": "uri", "value": "http://xmlns.com/foaf/0.1/maker"}, "isValueOf": {"type": "uri", "value": "http://dbtune.org/musicbrainz/resource/track/d57449e8-624d-4e46-8cb9-981836ebbcab"}}, {"property": {"type": "uri", "value": "http://xmlns.com/foaf/0.1/maker"}, "isValueOf": {"type": "uri", "value": "http://dbtune.org/musicbrainz/resource/track/d681545d-07c6-4a51-9ca9-b88bf884a98f"}}, {"property": {"type": "uri", "value": "http://xmlns.com/foaf/0.1/maker"}, "isValueOf": {"type": "uri", "value": "http://dbtune.org/musicbrainz/resource/track/db8cf97e-2588-4525-9f8d-91049fc1daaf"}}, {"property": {"type": "uri", "value": "http://xmlns.com/foaf/0.1/maker"}, "isValueOf": {"type": "uri", "value": "http://dbtune.org/musicbrainz/resource/track/dbfd26a8-3eac-40dd-981c-3ec6f38349a8"}}, {"property": {"type": "uri", "value": "http://xmlns.com/foaf/0.1/maker"}, "isValueOf": {"type": "uri", "value": "http://dbtune.org/musicbrainz/resource/track/de753842-4da3-449b-bc87-055f2036f7ea"}}, {"property": {"type": "uri", "value": "http://xmlns.com/foaf/0.1/maker"}, "isValueOf": {"type": "uri", "value": "http://dbtune.org/musicbrainz/resource/track/e2f4f9f1-3617-4491-910d-dc2a55e2a659"}}, {"property": {"type": "uri", "value": "http://xmlns.com/foaf/0.1/maker"}, "isValueOf": {"type": "uri", "value": "http://dbtune.org/musicbrainz/resource/track/e67d571f-7440-4f58-b768-b1d9e62a814e"}}, {"property": {"type": "uri", "value": "http://xmlns.com/foaf/0.1/maker"}, "isValueOf": {"type": "uri", "value": "http://dbtune.org/musicbrainz/resource/track/ee83ed12-d93d-4569-861f-b2635e8f1254"}}, {"property": {"type": "uri", "value": "http://xmlns.com/foaf/0.1/maker"}, "isValueOf": {"type": "uri", "value": "http://dbtune.org/musicbrainz/resource/track/f7b95ad8-2426-4e80-923c-48d6effed87b"}}, {"property": {"type": "uri", "value": "http://xmlns.com/foaf/0.1/maker"}, "isValueOf": {"type": "uri", "value": "http://dbtune.org/musicbrainz/resource/track/f862577d-04e3-4aa9-9977-7bc11903eb77"}}, {"property": {"type": "uri", "value": "http://xmlns.com/foaf/0.1/maker"}, "isValueOf": {"type": "uri", "value": "http://dbtune.org/musicbrainz/resource/track/f8ad8c73-3ef0-451d-9d4c-ddfeccddbc55"}}, {"property": {"type": "uri", "value": "http://xmlns.com/foaf/0.1/maker"}, "isValueOf": {"type": "uri", "value": "http://dbtune.org/musicbrainz/resource/track/ff37a451-cc39-454c-91c6-35d5e38cc1fd"}}]