[{"property": {"type": "uri", "value": "http://dbtune.org/musicbrainz/resource/vocab/artist_quality"}, "hasValue": {"datatype": "http://www.w3.org/2001/XMLSchema#short", "type": "typed-literal", "value": "-1"}}, {"property": {"type": "uri", "value": "http://dbtune.org/musicbrainz/resource/vocab/sortname"}, "hasValue": {"type": "literal", "value": "Moegi no koko iinkai"}}, {"property": {"type": "uri", "value": "http://purl.org/ontology/mo/musicbrainz"}, "hasValue": {"type": "uri", "value": "http://musicbrainz.org/artist/c21fad4b-c87a-42d2-a763-d3eb7607ffe8"}}, {"property": {"type": "uri", "value": "http://www.w3.org/1999/02/22-rdf-syntax-ns#type"}, "hasValue": {"type": "uri", "value": "http://purl.org/ontology/mo/MusicArtist"}}, {"property": {"type": "uri", "value": "http://www.w3.org/2000/01/rdf-schema#label"}, "hasValue": {"type": "literal", "value": "Moegi no koko iinkai"}}, {"property": {"type": "uri", "value": "http://www.w3.org/2002/07/owl#sameAs"}, "hasValue": {"type": "uri", "value": "http://www.bbc.co.uk/music/artists/c21fad4b-c87a-42d2-a763-d3eb7607ffe8#artist"}}, {"property": {"type": "uri", "value": "http://xmlns.com/foaf/0.1/name"}, "hasValue": {"type": "literal", "value": "Moegi no koko iinkai"}}, {"property": {"type": "uri", "value": "http://xmlns.com/foaf/0.1/maker"}, "isValueOf": {"type": "uri", "value": "http://dbtune.org/musicbrainz/resource/track/51fdcd2e-4fcb-4309-b92c-5deadf534505"}}, {"property": {"type": "uri", "value": "http://xmlns.com/foaf/0.1/maker"}, "isValueOf": {"type": "uri", "value": "http://dbtune.org/musicbrainz/resource/track/8eca12e0-036e-4d2a-b7d6-2944664f5f9d"}}]