[{"property": {"type": "uri", "value": "http://dbtune.org/musicbrainz/resource/vocab/artist_quality"}, "hasValue": {"datatype": "http://www.w3.org/2001/XMLSchema#short", "type": "typed-literal", "value": "-1"}}, {"property": {"type": "uri", "value": "http://dbtune.org/musicbrainz/resource/vocab/sortname"}, "hasValue": {"type": "literal", "value": "Musica Latina"}}, {"property": {"type": "uri", "value": "http://purl.org/ontology/mo/musicbrainz"}, "hasValue": {"type": "uri", "value": "http://musicbrainz.org/artist/2f08e4ab-680c-42d3-a937-6e3e98073402"}}, {"property": {"type": "uri", "value": "http://www.w3.org/1999/02/22-rdf-syntax-ns#type"}, "hasValue": {"type": "uri", "value": "http://purl.org/ontology/mo/MusicArtist"}}, {"property": {"type": "uri", "value": "http://www.w3.org/2000/01/rdf-schema#label"}, "hasValue": {"type": "literal", "value": "Musica Latina"}}, {"property": {"type": "uri", "value": "http://www.w3.org/2002/07/owl#sameAs"}, "hasValue": {"type": "uri", "value": "http://www.bbc.co.uk/music/artists/2f08e4ab-680c-42d3-a937-6e3e98073402#artist"}}, {"property": {"type": "uri", "value": "http://xmlns.com/foaf/0.1/name"}, "hasValue": {"type": "literal", "value": "Musica Latina"}}, {"property": {"type": "uri", "value": "http://xmlns.com/foaf/0.1/maker"}, "isValueOf": {"type": "uri", "value": "http://dbtune.org/musicbrainz/resource/track/016fb186-0ebf-46fa-a750-f9610bb90335"}}, {"property": {"type": "uri", "value": "http://xmlns.com/foaf/0.1/maker"}, "isValueOf": {"type": "uri", "value": "http://dbtune.org/musicbrainz/resource/track/01b15f6b-5574-4c3b-9fcd-530ef2fb2179"}}, {"property": {"type": "uri", "value": "http://xmlns.com/foaf/0.1/maker"}, "isValueOf": {"type": "uri", "value": "http://dbtune.org/musicbrainz/resource/track/84f30d7a-5485-4e6c-9b53-9bbceb8f43e1"}}, {"property": {"type": "uri", "value": "http://xmlns.com/foaf/0.1/maker"}, "isValueOf": {"type": "uri", "value": "http://dbtune.org/musicbrainz/resource/track/934b60ea-0232-4ebe-86e8-24ea2376c525"}}, {"property": {"type": "uri", "value": "http://xmlns.com/foaf/0.1/maker"}, "isValueOf": {"type": "uri", "value": "http://dbtune.org/musicbrainz/resource/track/c2b19425-d78c-41df-9db1-ff046124c6cc"}}, {"property": {"type": "uri", "value": "http://xmlns.com/foaf/0.1/maker"}, "isValueOf": {"type": "uri", "value": "http://dbtune.org/musicbrainz/resource/track/d0694427-386e-444e-83ec-50cb51ee9272"}}, {"property": {"type": "uri", "value": "http://xmlns.com/foaf/0.1/maker"}, "isValueOf": {"type": "uri", "value": "http://dbtune.org/musicbrainz/resource/track/f868d715-547e-4ae0-b800-377af2f83f81"}}]