[{"property": {"type": "uri", "value": "http://dbtune.org/musicbrainz/resource/vocab/artist_quality"}, "hasValue": {"datatype": "http://www.w3.org/2001/XMLSchema#short", "type": "typed-literal", "value": "-1"}}, {"property": {"type": "uri", "value": "http://dbtune.org/musicbrainz/resource/vocab/artist_type"}, "hasValue": {"datatype": "http://www.w3.org/2001/XMLSchema#short", "type": "typed-literal", "value": "2"}}, {"property": {"type": "uri", "value": "http://dbtune.org/musicbrainz/resource/vocab/sortname"}, "hasValue": {"type": "literal", "value": "M\u00e4rz"}}, {"property": {"type": "uri", "value": "http://purl.org/ontology/mo/musicbrainz"}, "hasValue": {"type": "uri", "value": "http://musicbrainz.org/artist/acab022f-71fe-458b-817a-4d386d710f10"}}, {"property": {"type": "uri", "value": "http://www.w3.org/1999/02/22-rdf-syntax-ns#type"}, "hasValue": {"type": "uri", "value": "http://purl.org/ontology/mo/MusicArtist"}}, {"property": {"type": "uri", "value": "http://www.w3.org/2000/01/rdf-schema#label"}, "hasValue": {"type": "literal", "value": "M\u00e4rz"}}, {"property": {"type": "uri", "value": "http://www.w3.org/2002/07/owl#sameAs"}, "hasValue": {"type": "uri", "value": "http://www.bbc.co.uk/music/artists/acab022f-71fe-458b-817a-4d386d710f10#artist"}}, {"property": {"type": "uri", "value": "http://xmlns.com/foaf/0.1/homepage"}, "hasValue": {"type": "uri", "value": "http://www.maerzmusik.net/"}}, {"property": {"type": "uri", "value": "http://xmlns.com/foaf/0.1/member"}, "hasValue": {"type": "uri", "value": "http://dbtune.org/musicbrainz/resource/artist/100b89f8-2190-42f8-a254-a261a232ffe7"}}, {"property": {"type": "uri", "value": "http://xmlns.com/foaf/0.1/member"}, "hasValue": {"type": "uri", "value": "http://dbtune.org/musicbrainz/resource/artist/b26bc71f-5076-4f6b-9dbd-cd35a8aedcf7"}}, {"property": {"type": "uri", "value": "http://xmlns.com/foaf/0.1/name"}, "hasValue": {"type": "literal", "value": "M\u00e4rz"}}, {"property": {"type": "uri", "value": "http://xmlns.com/foaf/0.1/maker"}, "isValueOf": {"type": "uri", "value": "http://dbtune.org/musicbrainz/resource/record/59b8b304-abde-47bd-92e3-9ffbe87a8368"}}, {"property": {"type": "uri", "value": "http://xmlns.com/foaf/0.1/maker"}, "isValueOf": {"type": "uri", "value": "http://dbtune.org/musicbrainz/resource/record/e982e686-a2b1-470e-95ce-f9c01fadf9be"}}, {"property": {"type": "uri", "value": "http://xmlns.com/foaf/0.1/maker"}, "isValueOf": {"type": "uri", "value": "http://dbtune.org/musicbrainz/resource/track/06b3a96c-1b75-4252-9975-00fedf8def44"}}, {"property": {"type": "uri", "value": "http://xmlns.com/foaf/0.1/maker"}, "isValueOf": {"type": "uri", "value": "http://dbtune.org/musicbrainz/resource/track/088ac968-fcb7-4e91-bdec-50eed11d3fed"}}, {"property": {"type": "uri", "value": "http://xmlns.com/foaf/0.1/maker"}, "isValueOf": {"type": "uri", "value": "http://dbtune.org/musicbrainz/resource/track/2541f2b3-0ca4-4776-a023-615001e07b24"}}, {"property": {"type": "uri", "value": "http://xmlns.com/foaf/0.1/maker"}, "isValueOf": {"type": "uri", "value": "http://dbtune.org/musicbrainz/resource/track/25d8dd82-9ed5-4dff-96ce-02353f4ac1f4"}}, {"property": {"type": "uri", "value": "http://xmlns.com/foaf/0.1/maker"}, "isValueOf": {"type": "uri", "value": "http://dbtune.org/musicbrainz/resource/track/2bb9953a-6880-4b5b-8207-377d8c8327c7"}}, {"property": {"type": "uri", "value": "http://xmlns.com/foaf/0.1/maker"}, "isValueOf": {"type": "uri", "value": "http://dbtune.org/musicbrainz/resource/track/2d7e13ae-df66-44d2-b536-d0363abbc956"}}, {"property": {"type": "uri", "value": "http://xmlns.com/foaf/0.1/maker"}, "isValueOf": {"type": "uri", "value": "http://dbtune.org/musicbrainz/resource/track/2f2682b4-9a80-4bb0-b88c-18f71dcad987"}}, {"property": {"type": "uri", "value": "http://xmlns.com/foaf/0.1/maker"}, "isValueOf": {"type": "uri", "value": "http://dbtune.org/musicbrainz/resource/track/33bb5162-2004-425b-9af0-1fff3d6ed37e"}}, {"property": {"type": "uri", "value": "http://xmlns.com/foaf/0.1/maker"}, "isValueOf": {"type": "uri", "value": "http://dbtune.org/musicbrainz/resource/track/3775e9ea-1b5f-461b-9613-5576f94b6b08"}}, {"property": {"type": "uri", "value": "http://xmlns.com/foaf/0.1/maker"}, "isValueOf": {"type": "uri", "value": "http://dbtune.org/musicbrainz/resource/track/3d163d82-1a1d-4e54-9abd-a51053030071"}}, {"property": {"type": "uri", "value": "http://xmlns.com/foaf/0.1/maker"}, "isValueOf": {"type": "uri", "value": "http://dbtune.org/musicbrainz/resource/track/48b4d8aa-66fc-4ba8-b9db-67d9c12f3413"}}, {"property": {"type": "uri", "value": "http://xmlns.com/foaf/0.1/maker"}, "isValueOf": {"type": "uri", "value": "http://dbtune.org/musicbrainz/resource/track/524946a8-282f-4cde-94f6-dabf297794ca"}}, {"property": {"type": "uri", "value": "http://xmlns.com/foaf/0.1/maker"}, "isValueOf": {"type": "uri", "value": "http://dbtune.org/musicbrainz/resource/track/585e0edb-ca47-492c-8dcc-03cf7a2b477f"}}, {"property": {"type": "uri", "value": "http://xmlns.com/foaf/0.1/maker"}, "isValueOf": {"type": "uri", "value": "http://dbtune.org/musicbrainz/resource/track/5f40e3c2-f838-4008-8d26-c289b2b5f977"}}, {"property": {"type": "uri", "value": "http://xmlns.com/foaf/0.1/maker"}, "isValueOf": {"type": "uri", "value": "http://dbtune.org/musicbrainz/resource/track/621dc2ef-6f69-40fe-8b9a-6f3be7588907"}}, {"property": {"type": "uri", "value": "http://xmlns.com/foaf/0.1/maker"}, "isValueOf": {"type": "uri", "value": "http://dbtune.org/musicbrainz/resource/track/64acc2a8-25e2-41ae-b171-7febaa260038"}}, {"property": {"type": "uri", "value": "http://xmlns.com/foaf/0.1/maker"}, "isValueOf": {"type": "uri", "value": "http://dbtune.org/musicbrainz/resource/track/6dc9a4e8-14e6-44b7-9196-c508e4f3ae3d"}}, {"property": {"type": "uri", "value": "http://xmlns.com/foaf/0.1/maker"}, "isValueOf": {"type": "uri", "value": "http://dbtune.org/musicbrainz/resource/track/77093c40-4d66-4f24-ba96-c8cee9be9df5"}}, {"property": {"type": "uri", "value": "http://xmlns.com/foaf/0.1/maker"}, "isValueOf": {"type": "uri", "value": "http://dbtune.org/musicbrainz/resource/track/794636ec-1f03-4e1a-b492-b26299d32b1b"}}, {"property": {"type": "uri", "value": "http://xmlns.com/foaf/0.1/maker"}, "isValueOf": {"type": "uri", "value": "http://dbtune.org/musicbrainz/resource/track/795f3fb0-ba2c-4d6d-bcf5-e7cd5926e003"}}, {"property": {"type": "uri", "value": "http://xmlns.com/foaf/0.1/maker"}, "isValueOf": {"type": "uri", "value": "http://dbtune.org/musicbrainz/resource/track/7b92b554-512d-40e5-9a37-0657d536d9e7"}}, {"property": {"type": "uri", "value": "http://xmlns.com/foaf/0.1/maker"}, "isValueOf": {"type": "uri", "value": "http://dbtune.org/musicbrainz/resource/track/89974aca-cc64-4f50-a6f2-f393a2ce00f2"}}, {"property": {"type": "uri", "value": "http://xmlns.com/foaf/0.1/maker"}, "isValueOf": {"type": "uri", "value": "http://dbtune.org/musicbrainz/resource/track/8e45852a-6bdd-4e4d-97a4-f93dd0b2c009"}}, {"property": {"type": "uri", "value": "http://xmlns.com/foaf/0.1/maker"}, "isValueOf": {"type": "uri", "value": "http://dbtune.org/musicbrainz/resource/track/959ea812-f17a-454a-8742-cc6a91e982cd"}}, {"property": {"type": "uri", "value": "http://xmlns.com/foaf/0.1/maker"}, "isValueOf": {"type": "uri", "value": "http://dbtune.org/musicbrainz/resource/track/98a3a347-a631-4158-98b8-12b1a50bea00"}}, {"property": {"type": "uri", "value": "http://xmlns.com/foaf/0.1/maker"}, "isValueOf": {"type": "uri", "value": "http://dbtune.org/musicbrainz/resource/track/9dfae15e-83a3-4a58-bd7c-edb5f8e08969"}}, {"property": {"type": "uri", "value": "http://xmlns.com/foaf/0.1/maker"}, "isValueOf": {"type": "uri", "value": "http://dbtune.org/musicbrainz/resource/track/ac8ae195-40bd-4b69-8d87-f5bd22ff1174"}}, {"property": {"type": "uri", "value": "http://xmlns.com/foaf/0.1/maker"}, "isValueOf": {"type": "uri", "value": "http://dbtune.org/musicbrainz/resource/track/bf110b1c-1b7f-4047-b219-b691dad26557"}}, {"property": {"type": "uri", "value": "http://xmlns.com/foaf/0.1/maker"}, "isValueOf": {"type": "uri", "value": "http://dbtune.org/musicbrainz/resource/track/c064b18f-5550-42b1-960f-5dc0278ac1a9"}}, {"property": {"type": "uri", "value": "http://xmlns.com/foaf/0.1/maker"}, "isValueOf": {"type": "uri", "value": "http://dbtune.org/musicbrainz/resource/track/cea79c90-f94d-43cb-a860-fab3c7118486"}}, {"property": {"type": "uri", "value": "http://xmlns.com/foaf/0.1/maker"}, "isValueOf": {"type": "uri", "value": "http://dbtune.org/musicbrainz/resource/track/d5a9bb4c-4fe4-4650-b624-c77ced174a1b"}}, {"property": {"type": "uri", "value": "http://xmlns.com/foaf/0.1/maker"}, "isValueOf": {"type": "uri", "value": "http://dbtune.org/musicbrainz/resource/track/d72bd1d1-9e91-4e53-86c3-2b0a3a8fc978"}}, {"property": {"type": "uri", "value": "http://xmlns.com/foaf/0.1/maker"}, "isValueOf": {"type": "uri", "value": "http://dbtune.org/musicbrainz/resource/track/fb9210bc-37c1-443d-b7b6-ebed3d195009"}}]