[{"property": {"type": "uri", "value": "http://dbtune.org/musicbrainz/resource/vocab/artist_quality"}, "hasValue": {"datatype": "http://www.w3.org/2001/XMLSchema#short", "type": "typed-literal", "value": "-1"}}, {"property": {"type": "uri", "value": "http://dbtune.org/musicbrainz/resource/vocab/artist_tag_count"}, "hasValue": {"datatype": "http://www.w3.org/2001/XMLSchema#int", "type": "typed-literal", "value": "1"}}, {"property": {"type": "uri", "value": "http://dbtune.org/musicbrainz/resource/vocab/artist_type"}, "hasValue": {"datatype": "http://www.w3.org/2001/XMLSchema#short", "type": "typed-literal", "value": "2"}}, {"property": {"type": "uri", "value": "http://dbtune.org/musicbrainz/resource/vocab/sortname"}, "hasValue": {"type": "literal", "value": "Sea Level"}}, {"property": {"type": "uri", "value": "http://purl.org/ontology/mo/musicbrainz"}, "hasValue": {"type": "uri", "value": "http://musicbrainz.org/artist/84db3721-9824-4010-a396-504177e154a8"}}, {"property": {"type": "uri", "value": "http://purl.org/vocab/bio/0.1/event"}, "hasValue": {"type": "uri", "value": "http://dbtune.org/musicbrainz/resource/artist/84db3721-9824-4010-a396-504177e154a8/birth"}}, {"property": {"type": "uri", "value": "http://purl.org/vocab/bio/0.1/event"}, "hasValue": {"type": "uri", "value": "http://dbtune.org/musicbrainz/resource/artist/84db3721-9824-4010-a396-504177e154a8/death"}}, {"property": {"type": "uri", "value": "http://www.holygoat.co.uk/owl/redwood/0.1/tags/taggedWithTag"}, "hasValue": {"type": "uri", "value": "http://dbtune.org/musicbrainz/resource/tag/71"}}, {"property": {"type": "uri", "value": "http://www.w3.org/1999/02/22-rdf-syntax-ns#type"}, "hasValue": {"type": "uri", "value": "http://purl.org/ontology/mo/MusicArtist"}}, {"property": {"type": "uri", "value": "http://www.w3.org/2000/01/rdf-schema#label"}, "hasValue": {"type": "literal", "value": "Sea Level"}}, {"property": {"type": "uri", "value": "http://www.w3.org/2002/07/owl#sameAs"}, "hasValue": {"type": "uri", "value": "http://dbpedia.org/resource/Sea_Level_%28band%29"}}, {"property": {"type": "uri", "value": "http://www.w3.org/2002/07/owl#sameAs"}, "hasValue": {"type": "uri", "value": "http://www.bbc.co.uk/music/artists/84db3721-9824-4010-a396-504177e154a8#artist"}}, {"property": {"type": "uri", "value": "http://xmlns.com/foaf/0.1/member"}, "hasValue": {"type": "uri", "value": "http://dbtune.org/musicbrainz/resource/artist/c77c62d3-f025-429c-bcae-91e83dd3f516"}}, {"property": {"type": "uri", "value": "http://xmlns.com/foaf/0.1/member"}, "hasValue": {"type": "uri", "value": "http://dbtune.org/musicbrainz/resource/artist/e7da059f-038d-4169-b1b0-1985c9a36c9b"}}, {"property": {"type": "uri", "value": "http://xmlns.com/foaf/0.1/name"}, "hasValue": {"type": "literal", "value": "Sea Level"}}, {"property": {"type": "uri", "value": "http://xmlns.com/foaf/0.1/maker"}, "isValueOf": {"type": "uri", "value": "http://dbtune.org/musicbrainz/resource/record/9cfa5169-ad2d-4e7a-ac78-7c84a820c5e8"}}, {"property": {"type": "uri", "value": "http://xmlns.com/foaf/0.1/maker"}, "isValueOf": {"type": "uri", "value": "http://dbtune.org/musicbrainz/resource/record/c0a360dd-d448-482f-9bd4-97514438773d"}}, {"property": {"type": "uri", "value": "http://xmlns.com/foaf/0.1/maker"}, "isValueOf": {"type": "uri", "value": "http://dbtune.org/musicbrainz/resource/record/e224e88e-f697-407d-8268-e54fe141c750"}}, {"property": {"type": "uri", "value": "http://xmlns.com/foaf/0.1/maker"}, "isValueOf": {"type": "uri", "value": "http://dbtune.org/musicbrainz/resource/record/ec257228-b281-4e4b-90e7-2368bb7e1f8e"}}, {"property": {"type": "uri", "value": "http://xmlns.com/foaf/0.1/maker"}, "isValueOf": {"type": "uri", "value": "http://dbtune.org/musicbrainz/resource/track/00c95fad-ee34-4764-a09b-a7d2c71a4e66"}}, {"property": {"type": "uri", "value": "http://xmlns.com/foaf/0.1/maker"}, "isValueOf": {"type": "uri", "value": "http://dbtune.org/musicbrainz/resource/track/020916e9-c45f-435f-b4cc-3dc197fd8ed9"}}, {"property": {"type": "uri", "value": "http://xmlns.com/foaf/0.1/maker"}, "isValueOf": {"type": "uri", "value": "http://dbtune.org/musicbrainz/resource/track/075d9d1f-d72f-4db7-bd47-22009ad98dfb"}}, {"property": {"type": "uri", "value": "http://xmlns.com/foaf/0.1/maker"}, "isValueOf": {"type": "uri", "value": "http://dbtune.org/musicbrainz/resource/track/07b70927-aa50-46fb-959c-3f71dc783b76"}}, {"property": {"type": "uri", "value": "http://xmlns.com/foaf/0.1/maker"}, "isValueOf": {"type": "uri", "value": "http://dbtune.org/musicbrainz/resource/track/080dd714-6e2d-4441-8e20-aee8ea548b8c"}}, {"property": {"type": "uri", "value": "http://xmlns.com/foaf/0.1/maker"}, "isValueOf": {"type": "uri", "value": "http://dbtune.org/musicbrainz/resource/track/19cf9403-8f17-475f-838d-69ace4cb5473"}}, {"property": {"type": "uri", "value": "http://xmlns.com/foaf/0.1/maker"}, "isValueOf": {"type": "uri", "value": "http://dbtune.org/musicbrainz/resource/track/2d16d8fe-28d4-4393-8f56-8e5237c4c4c8"}}, {"property": {"type": "uri", "value": "http://xmlns.com/foaf/0.1/maker"}, "isValueOf": {"type": "uri", "value": "http://dbtune.org/musicbrainz/resource/track/30c64b8c-c7a4-474b-90d5-ef696737f50d"}}, {"property": {"type": "uri", "value": "http://xmlns.com/foaf/0.1/maker"}, "isValueOf": {"type": "uri", "value": "http://dbtune.org/musicbrainz/resource/track/3304d519-d9c0-493a-bdc1-da277d49e445"}}, {"property": {"type": "uri", "value": "http://xmlns.com/foaf/0.1/maker"}, "isValueOf": {"type": "uri", "value": "http://dbtune.org/musicbrainz/resource/track/34793c06-da73-46df-8de3-4b615417b4d1"}}, {"property": {"type": "uri", "value": "http://xmlns.com/foaf/0.1/maker"}, "isValueOf": {"type": "uri", "value": "http://dbtune.org/musicbrainz/resource/track/36a892d7-e269-41ea-ac1e-78e024039c89"}}, {"property": {"type": "uri", "value": "http://xmlns.com/foaf/0.1/maker"}, "isValueOf": {"type": "uri", "value": "http://dbtune.org/musicbrainz/resource/track/37157c73-2e16-44d2-8d24-c4c60842ab52"}}, {"property": {"type": "uri", "value": "http://xmlns.com/foaf/0.1/maker"}, "isValueOf": {"type": "uri", "value": "http://dbtune.org/musicbrainz/resource/track/3e99555d-8b66-4e78-bebb-4f8126c27cd2"}}, {"property": {"type": "uri", "value": "http://xmlns.com/foaf/0.1/maker"}, "isValueOf": {"type": "uri", "value": "http://dbtune.org/musicbrainz/resource/track/470b7248-1261-43a7-928f-f66da1e9cd02"}}, {"property": {"type": "uri", "value": "http://xmlns.com/foaf/0.1/maker"}, "isValueOf": {"type": "uri", "value": "http://dbtune.org/musicbrainz/resource/track/4a83bdc7-8d77-497a-9748-e9a0687a2fe3"}}, {"property": {"type": "uri", "value": "http://xmlns.com/foaf/0.1/maker"}, "isValueOf": {"type": "uri", "value": "http://dbtune.org/musicbrainz/resource/track/4d32bb59-588e-4492-bd4a-59574e97485a"}}, {"property": {"type": "uri", "value": "http://xmlns.com/foaf/0.1/maker"}, "isValueOf": {"type": "uri", "value": "http://dbtune.org/musicbrainz/resource/track/4fcdb1c5-419a-4681-854a-fa54b6495eb4"}}, {"property": {"type": "uri", "value": "http://xmlns.com/foaf/0.1/maker"}, "isValueOf": {"type": "uri", "value": "http://dbtune.org/musicbrainz/resource/track/5af4d914-a444-4871-8bab-f9fed1e8b706"}}, {"property": {"type": "uri", "value": "http://xmlns.com/foaf/0.1/maker"}, "isValueOf": {"type": "uri", "value": "http://dbtune.org/musicbrainz/resource/track/5ba1d48e-e5fb-4075-aa60-525aa6a4365f"}}, {"property": {"type": "uri", "value": "http://xmlns.com/foaf/0.1/maker"}, "isValueOf": {"type": "uri", "value": "http://dbtune.org/musicbrainz/resource/track/6a5a453a-4ee9-486a-8878-09dfb8e3d780"}}, {"property": {"type": "uri", "value": "http://xmlns.com/foaf/0.1/maker"}, "isValueOf": {"type": "uri", "value": "http://dbtune.org/musicbrainz/resource/track/747ad93e-2638-4d23-ac06-98fad5f764be"}}, {"property": {"type": "uri", "value": "http://xmlns.com/foaf/0.1/maker"}, "isValueOf": {"type": "uri", "value": "http://dbtune.org/musicbrainz/resource/track/7b5aac9b-1a94-46d0-b249-85c7df98a1bb"}}, {"property": {"type": "uri", "value": "http://xmlns.com/foaf/0.1/maker"}, "isValueOf": {"type": "uri", "value": "http://dbtune.org/musicbrainz/resource/track/7d70d604-e6e9-4304-a2da-95021eaad04d"}}, {"property": {"type": "uri", "value": "http://xmlns.com/foaf/0.1/maker"}, "isValueOf": {"type": "uri", "value": "http://dbtune.org/musicbrainz/resource/track/7da20f1d-aec6-4310-8868-aa9bdd84a6d9"}}, {"property": {"type": "uri", "value": "http://xmlns.com/foaf/0.1/maker"}, "isValueOf": {"type": "uri", "value": "http://dbtune.org/musicbrainz/resource/track/8bdd26d4-233c-4d15-8720-7a506f06a2c9"}}, {"property": {"type": "uri", "value": "http://xmlns.com/foaf/0.1/maker"}, "isValueOf": {"type": "uri", "value": "http://dbtune.org/musicbrainz/resource/track/8f7ffdb9-e3a7-4acd-a199-39ef346c23be"}}, {"property": {"type": "uri", "value": "http://xmlns.com/foaf/0.1/maker"}, "isValueOf": {"type": "uri", "value": "http://dbtune.org/musicbrainz/resource/track/a1c91f74-9a97-47cf-bf62-4e4091239fa7"}}, {"property": {"type": "uri", "value": "http://xmlns.com/foaf/0.1/maker"}, "isValueOf": {"type": "uri", "value": "http://dbtune.org/musicbrainz/resource/track/a584771c-200f-471f-a923-dd8de27f0601"}}, {"property": {"type": "uri", "value": "http://xmlns.com/foaf/0.1/maker"}, "isValueOf": {"type": "uri", "value": "http://dbtune.org/musicbrainz/resource/track/ae41f445-9227-47f2-9711-ad34e60cb9f6"}}, {"property": {"type": "uri", "value": "http://xmlns.com/foaf/0.1/maker"}, "isValueOf": {"type": "uri", "value": "http://dbtune.org/musicbrainz/resource/track/af5229f1-51c3-490e-a8a3-6f7d0ec7ddfd"}}, {"property": {"type": "uri", "value": "http://xmlns.com/foaf/0.1/maker"}, "isValueOf": {"type": "uri", "value": "http://dbtune.org/musicbrainz/resource/track/b0cedf98-23ba-43ed-bcfc-147eda45ce9c"}}, {"property": {"type": "uri", "value": "http://xmlns.com/foaf/0.1/maker"}, "isValueOf": {"type": "uri", "value": "http://dbtune.org/musicbrainz/resource/track/b2e517e8-20c6-4378-bb5f-c5f7ca4c90df"}}, {"property": {"type": "uri", "value": "http://xmlns.com/foaf/0.1/maker"}, "isValueOf": {"type": "uri", "value": "http://dbtune.org/musicbrainz/resource/track/b49d2c46-988b-4a6a-99a3-19e7a7542730"}}, {"property": {"type": "uri", "value": "http://xmlns.com/foaf/0.1/maker"}, "isValueOf": {"type": "uri", "value": "http://dbtune.org/musicbrainz/resource/track/b893e3f2-b54e-4a15-bc6d-ad09ef8ef26f"}}, {"property": {"type": "uri", "value": "http://xmlns.com/foaf/0.1/maker"}, "isValueOf": {"type": "uri", "value": "http://dbtune.org/musicbrainz/resource/track/bc6f8f2b-61e2-4d83-b986-ff83c192a128"}}, {"property": {"type": "uri", "value": "http://xmlns.com/foaf/0.1/maker"}, "isValueOf": {"type": "uri", "value": "http://dbtune.org/musicbrainz/resource/track/c07be0bb-f92b-42f0-9a11-7dad7833ece2"}}, {"property": {"type": "uri", "value": "http://xmlns.com/foaf/0.1/maker"}, "isValueOf": {"type": "uri", "value": "http://dbtune.org/musicbrainz/resource/track/c084aac8-cd19-4a85-9d91-5724a7e7352e"}}, {"property": {"type": "uri", "value": "http://xmlns.com/foaf/0.1/maker"}, "isValueOf": {"type": "uri", "value": "http://dbtune.org/musicbrainz/resource/track/c6b5f5f5-d881-4a8d-965b-a6b75e042022"}}, {"property": {"type": "uri", "value": "http://xmlns.com/foaf/0.1/maker"}, "isValueOf": {"type": "uri", "value": "http://dbtune.org/musicbrainz/resource/track/ca6d2914-86d3-4716-9ef5-2152e22b8ab1"}}, {"property": {"type": "uri", "value": "http://xmlns.com/foaf/0.1/maker"}, "isValueOf": {"type": "uri", "value": "http://dbtune.org/musicbrainz/resource/track/cba66f57-ed1c-49dc-8b6f-c085394204ac"}}, {"property": {"type": "uri", "value": "http://xmlns.com/foaf/0.1/maker"}, "isValueOf": {"type": "uri", "value": "http://dbtune.org/musicbrainz/resource/track/cd019947-5b2e-4d37-8b19-f0ab09e9d7b9"}}, {"property": {"type": "uri", "value": "http://xmlns.com/foaf/0.1/maker"}, "isValueOf": {"type": "uri", "value": "http://dbtune.org/musicbrainz/resource/track/cff2693c-27d0-4871-b31f-c59c64dc3d8b"}}, {"property": {"type": "uri", "value": "http://xmlns.com/foaf/0.1/maker"}, "isValueOf": {"type": "uri", "value": "http://dbtune.org/musicbrainz/resource/track/d7ebdbb1-681e-4ab2-a108-9c5f7b84de35"}}, {"property": {"type": "uri", "value": "http://xmlns.com/foaf/0.1/maker"}, "isValueOf": {"type": "uri", "value": "http://dbtune.org/musicbrainz/resource/track/dbccfc0c-b623-4ada-ad60-95b34922a9f9"}}, {"property": {"type": "uri", "value": "http://xmlns.com/foaf/0.1/maker"}, "isValueOf": {"type": "uri", "value": "http://dbtune.org/musicbrainz/resource/track/dfc742b7-1593-4607-8198-f3c2d793521c"}}, {"property": {"type": "uri", "value": "http://xmlns.com/foaf/0.1/maker"}, "isValueOf": {"type": "uri", "value": "http://dbtune.org/musicbrainz/resource/track/e06104c0-3db7-4441-b0cc-a29331559a7e"}}, {"property": {"type": "uri", "value": "http://xmlns.com/foaf/0.1/maker"}, "isValueOf": {"type": "uri", "value": "http://dbtune.org/musicbrainz/resource/track/e0a06b88-ccc9-4707-825c-ceed6e9575c4"}}, {"property": {"type": "uri", "value": "http://xmlns.com/foaf/0.1/maker"}, "isValueOf": {"type": "uri", "value": "http://dbtune.org/musicbrainz/resource/track/f803a2c6-7800-4111-95d6-89b68854041c"}}, {"property": {"type": "uri", "value": "http://xmlns.com/foaf/0.1/maker"}, "isValueOf": {"type": "uri", "value": "http://dbtune.org/musicbrainz/resource/track/fc627e0c-b91a-4029-9221-a0d3fe157523"}}]